{ "backgroundcolor":"#000000",
 "height":80,
 "layers":[
        {
         "compression":"zlib",
         "data":"eJzt1U0KwjAQQOHYnYcRXFjweD26FupCpHUmmZ+kvIGHmyDzmRanUpZp7Iqy7H3x4sWLFy9evON1dq\/Wl+2V7tDqcvGWhMnyxku\/J8qbYdsbT28KSDAe3hyJbKy9OQrd4K3zJq1fNXjxnsW6Dl68ePGOMnjx4sU7yuDFixevZh6X9hyth94a87rv891t+5T2OT+qd94M0ubBvZH3q7D+9WrNeH29SqvIqzFHeiusYq\/UvO57b0jqrbSqvBJ3xP9vg\/XI+3P22mEO95tuMjaLnuFsk9Hdqt7fbJ+BVfQ89\/gOO3q7cjc4m7xZ\/kCvyL1ntzhnYK3xit2TYk9Dj5dXbe8kC6\/ELj3v\/Ztaexfn7261e+0UldW9ExERERERERERUXAvpj1eEA==",
         "encoding":"base64",
         "height":80,
         "name":"back",
         "opacity":0.5,
         "type":"tilelayer",
         "visible":true,
         "width":60,
         "x":0,
         "y":0
        }, 
        {
         "compression":"zlib",
         "data":"eJzt1UEKgCAQQFFbdpsWbbz\/xSJIaBMYljX4HsxOYf5GUwIAAAAAAAAAgLjWqX0iad03Wi9ABPn4T5aG2e\/nAG902fGp\/\/cPzfMPZ5TOEZvf9nVfz9bi687evcUonVdG6z2r3fPuuQhq94zSAwAAAAAApLQBfmMUiw==",
         "encoding":"base64",
         "height":80,
         "name":"front",
         "opacity":1,
         "type":"tilelayer",
         "visible":true,
         "width":60,
         "x":0,
         "y":0
        }, 
        {
         "color":"#5555ff",
         "draworder":"topdown",
         "height":0,
         "name":"mods",
         "objects":[],
         "opacity":1,
         "type":"objectgroup",
         "visible":true,
         "width":0,
         "x":0,
         "y":0
        }, 
        {
         "draworder":"topdown",
         "height":0,
         "name":"objects",
         "objects":[
                {
                 "gid":389,
                 "height":40,
                 "id":813,
                 "name":"",
                 "properties":
                    {

                    },
                 "rotation":0,
                 "type":"",
                 "visible":true,
                 "width":8,
                 "x":160,
                 "y":352
                }, 
                {
                 "gid":389,
                 "height":40,
                 "id":814,
                 "name":"",
                 "properties":
                    {

                    },
                 "rotation":0,
                 "type":"",
                 "visible":true,
                 "width":8,
                 "x":288,
                 "y":352
                }, 
                {
                 "gid":410,
                 "height":8,
                 "id":815,
                 "name":"",
                 "properties":
                    {

                    },
                 "rotation":0,
                 "type":"",
                 "visible":true,
                 "width":8,
                 "x":176,
                 "y":320
                }, 
                {
                 "gid":410,
                 "height":8,
                 "id":816,
                 "name":"",
                 "properties":
                    {

                    },
                 "rotation":0,
                 "type":"",
                 "visible":true,
                 "width":8,
                 "x":272,
                 "y":320
                }, 
                {
                 "gid":324,
                 "height":24,
                 "id":817,
                 "name":"",
                 "properties":
                    {

                    },
                 "rotation":0,
                 "type":"",
                 "visible":true,
                 "width":48,
                 "x":232,
                 "y":352
                }, 
                {
                 "gid":344,
                 "height":32,
                 "id":818,
                 "name":"",
                 "properties":
                    {
                     "parameters":"{ \"treasurePools\" : [ \"alliancefridge\" ] }"
                    },
                 "rotation":0,
                 "type":"",
                 "visible":true,
                 "width":24,
                 "x":176,
                 "y":352
                }, 
                {
                 "gid":377,
                 "height":48,
                 "id":819,
                 "name":"",
                 "properties":
                    {

                    },
                 "rotation":0,
                 "type":"",
                 "visible":true,
                 "width":16,
                 "x":208,
                 "y":352
                }, 
                {
                 "gid":320,
                 "height":48,
                 "id":820,
                 "name":"",
                 "properties":
                    {

                    },
                 "rotation":0,
                 "type":"",
                 "visible":true,
                 "width":16,
                 "x":264,
                 "y":296
                }, 
                {
                 "gid":8,
                 "height":8,
                 "id":823,
                 "name":"",
                 "properties":
                    {

                    },
                 "rotation":0,
                 "type":"",
                 "visible":true,
                 "width":8,
                 "x":328,
                 "y":368
                }, 
                {
                 "gid":7,
                 "height":8,
                 "id":824,
                 "name":"",
                 "properties":
                    {

                    },
                 "rotation":0,
                 "type":"",
                 "visible":true,
                 "width":8,
                 "x":120,
                 "y":368
                }],
         "opacity":1,
         "type":"objectgroup",
         "visible":true,
         "width":0,
         "x":0,
         "y":0
        }, 
        {
         "color":"#ffff00",
         "draworder":"topdown",
         "height":0,
         "name":"wiring",
         "objects":[],
         "opacity":1,
         "type":"objectgroup",
         "visible":true,
         "width":0,
         "x":0,
         "y":0
        }, 
        {
         "color":"#ff0000",
         "draworder":"topdown",
         "height":0,
         "name":"npc and monsters",
         "objects":[
                {
                 "height":8,
                 "id":821,
                 "name":"",
                 "properties":
                    {
                     "npc":"aegi",
                     "typeName":"aegivillager"
                    },
                 "rotation":0,
                 "type":"",
                 "visible":true,
                 "width":8,
                 "x":224,
                 "y":336
                }, 
                {
                 "height":8,
                 "id":822,
                 "name":"",
                 "properties":
                    {
                     "monster":"wildtrangii"
                    },
                 "rotation":0,
                 "type":"",
                 "visible":true,
                 "width":8,
                 "x":200,
                 "y":344
                }],
         "opacity":1,
         "type":"objectgroup",
         "visible":true,
         "width":0,
         "x":0,
         "y":0
        }, 
        {
         "draworder":"topdown",
         "height":0,
         "name":"anchors",
         "objects":[
                {
                 "gid":5,
                 "height":8,
                 "id":708,
                 "name":"",
                 "properties":
                    {

                    },
                 "rotation":0,
                 "type":"",
                 "visible":true,
                 "width":8,
                 "x":352,
                 "y":104
                }, 
                {
                 "gid":5,
                 "height":8,
                 "id":710,
                 "name":"",
                 "properties":
                    {

                    },
                 "rotation":0,
                 "type":"",
                 "visible":true,
                 "width":8,
                 "x":128,
                 "y":104
                }, 
                {
                 "gid":5,
                 "height":8,
                 "id":711,
                 "name":"",
                 "properties":
                    {

                    },
                 "rotation":0,
                 "type":"",
                 "visible":true,
                 "width":8,
                 "x":104,
                 "y":368
                }, 
                {
                 "gid":5,
                 "height":8,
                 "id":712,
                 "name":"",
                 "properties":
                    {

                    },
                 "rotation":0,
                 "type":"",
                 "visible":true,
                 "width":8,
                 "x":352,
                 "y":368
                }, 
                {
                 "gid":5,
                 "height":8,
                 "id":715,
                 "name":"",
                 "properties":
                    {

                    },
                 "rotation":0,
                 "type":"",
                 "visible":true,
                 "width":8,
                 "x":400,
                 "y":232
                }, 
                {
                 "gid":5,
                 "height":8,
                 "id":716,
                 "name":"",
                 "properties":
                    {

                    },
                 "rotation":0,
                 "type":"",
                 "visible":true,
                 "width":8,
                 "x":56,
                 "y":232
                }, 
                {
                 "gid":6,
                 "height":8,
                 "id":729,
                 "name":"",
                 "properties":
                    {

                    },
                 "rotation":0,
                 "type":"",
                 "visible":true,
                 "width":8,
                 "x":352,
                 "y":376
                }, 
                {
                 "gid":6,
                 "height":8,
                 "id":730,
                 "name":"",
                 "properties":
                    {

                    },
                 "rotation":0,
                 "type":"",
                 "visible":true,
                 "width":8,
                 "x":104,
                 "y":376
                }],
         "opacity":1,
         "type":"objectgroup",
         "visible":true,
         "width":0,
         "x":0,
         "y":0
        }],
 "nextobjectid":825,
 "orientation":"orthogonal",
 "properties":
    {

    },
 "renderorder":"right-down",
 "tileheight":8,
 "tilesets":[
        {
         "firstgid":1,
         "source":"..\/..\/..\/..\/..\/..\/assets\/packed\/tilesets\/packed\/miscellaneous.json"
        }, 
        {
         "firstgid":23,
         "source":"..\/..\/..\/..\/..\/..\/assets\/packed\/tilesets\/packed\/materials.json"
        }, 
        {
         "firstgid":218,
         "source":"..\/..\/..\/..\/..\/..\/assets\/packed\/tilesets\/packed\/liquids.json"
        }, 
        {
         "firstgid":246,
         "source":"..\/..\/..\/..\/tilesets\/avikan-custom\/theamaterials.json"
        }, 
        {
         "firstgid":320,
         "source":"..\/..\/..\/..\/tilesets\/avikan-custom\/theaobjects-alliance.json"
        }],
 "tilewidth":8,
 "version":1,
 "width":60
}